pyclick/__init__.py
pyclick/_beziercurve.py
pyclick/_utils.py
pyclick/humanclicker.py
pyclick/humancurve.py
pyclick-0.0.2.dist-info/METADATA
pyclick-0.0.2.dist-info/RECORD
pyclick-0.0.2.dist-info/WHEEL
pyclick-0.0.2.dist-info/top_level.txt
