Metadata-Version: 2.1
Name: pyclick
Version: 0.0.2
Summary: Human mouse movement simulation with python
Home-page: https://github.com/patrikoss/pyclick
Author: patrikoss
License: UNKNOWN
Platform: UNKNOWN
Classifier: Programming Language :: Python :: 3
Classifier: License :: OSI Approved :: MIT License
Classifier: Operating System :: OS Independent
